selfheal/__init__.py
selfheal/debug_viewer.py
selfheal/s3_storage.py
selfheal/slack.py
selfheal-1.0.2.dist-info/LICENSE
selfheal-1.0.2.dist-info/METADATA
selfheal-1.0.2.dist-info/WHEEL
selfheal-1.0.2.dist-info/top_level.txt
selfheal-1.0.2.dist-info/RECORD
