Metadata-Version: 2.1
Name: selfheal
Version: 1.0.2
Summary: Make all code self-healing with automatic debug state capture and LLM analysis
Home-page: https://github.com/openexcept/selfheal
Author: OpenExcept
Author-email: ai.observability.eng@gmail.com
Classifier: Development Status :: 4 - Beta
Classifier: Intended Audience :: Developers
Classifier: License :: OSI Approved :: Apache Software License
Classifier: Operating System :: OS Independent
Classifier: Programming Language :: Python :: 3
Classifier: Programming Language :: Python :: 3.7
Classifier: Programming Language :: Python :: 3.8
Classifier: Programming Language :: Python :: 3.9
Classifier: Programming Language :: Python :: 3.10
Classifier: Topic :: Software Development :: Debuggers
Requires-Python: >=3.7
License-File: LICENSE
Requires-Dist: boto3>=1.34.0
Requires-Dist: slack-sdk>=3.33.0
Requires-Dist: litellm>=1.52.0
Requires-Dist: openai>=1.54.0
Requires-Dist: streamlit>=1.30.0
